{
"16,11,06,102,Hawelon Benito,Stewart and Sons Fabrication" : 940.3,
"15,11,44,107,Morluniau Cecilia,Stewart and Sons Fabrication" : 4740.68,
"8,11,28,108,Morlun Adan,Stewart and Sons Fabrication" : 1738.26,
"10,11,49,107,Morluniau Cecilia,Stewart and Sons Fabrication" : 4074.1,
"17,11,32,107,Morluniau Cecilia,Stewart and Sons Fabrication" : 1753.17,
"10,12,10,103,Hawelon Claudio,Stewart and Sons Fabrication" : 4195.49,
"14,11,55,107,Morluniau Cecilia,Stewart and Sons Fabrication" : 278.52,
"14,11,01,102,Hawelon Benito,Stewart and Sons Fabrication" : 600.19,
"9,10,38,102,Hawelon Benito,Stewart and Sons Fabrication" : 1015.65,
"9,15,00,106,Scozzese Dylan,Stewart and Sons Fabrication" : 918.6,
"15,11,18,108,Morlun Adan,Stewart and Sons Fabrication" : 4545.38,
"6,11,33,107,Morluniau Cecilia,Stewart and Sons Fabrication" : 2144.62,
"16,11,45,107,Morluniau Cecilia,Stewart and Sons Fabrication" : 4543.31,
"9,11,37,107,Morluniau Cecilia,Stewart and Sons Fabrication" : 3544,
"7,10,05,102,Hawelon Benito,Stewart and Sons Fabrication" : 1200.9,
"7,15,03,106,Scozzese Dylan,Stewart and Sons Fabrication" : 962.2,
"7,11,31,107,Morluniau Cecilia,Stewart and Sons Fabrication" : 1843.33,
"8,11,58,107,Morluniau Cecilia,Stewart and Sons Fabrication" : 1673.77
}